tensorcat/__init__.py
tensorcat/cli.py
tensorcat/iterm2.py
tensorcat/tensorcat.py
tensorcat-0.1.5.dist-info/METADATA
tensorcat-0.1.5.dist-info/WHEEL
tensorcat-0.1.5.dist-info/entry_points.txt
tensorcat-0.1.5.dist-info/RECORD
