Metadata-Version: 2.1
Name: tensorcat
Version: 0.1.5
Summary: 
Author: Zhengyu Yang
Author-email: 25852061+zhengyu-yang@users.noreply.github.com
Requires-Python: >=3.8
Classifier: Programming Language :: Python :: 3
Classifier: Programming Language :: Python :: 3.8
Classifier: Programming Language :: Python :: 3.9
Classifier: Programming Language :: Python :: 3.10
Classifier: Programming Language :: Python :: 3.11
Classifier: Programming Language :: Python :: 3.12
Requires-Dist: iPython (>=8.4.0)
Requires-Dist: numpy (>=1.22.4)
Requires-Dist: pillow (>=9.4.0)
